README.md
setup.py
vitenstools/__init__.py
vitenstools/add_solutions_slm.py
vitenstools/chemistry.py
vitenstools/cijfer.py
vitenstools/grenswaarden.py
vitenstools/influx.py
vitenstools/phreeqpython_af.py
vitenstools/solution_methods.py
vitenstools.egg-info/PKG-INFO
vitenstools.egg-info/SOURCES.txt
vitenstools.egg-info/dependency_links.txt
vitenstools.egg-info/not-zip-safe
vitenstools.egg-info/top_level.txt