Metadata-Version: 1.0
Name: vitenstools
Version: 0.9.4
Summary: Vitens Specific Tools and Extensions for PhreeqPython
Home-page: https://github.com/AbelHeinsbroek/vitens
Author: Abel Heinsbroek
Author-email: abel.heinsbroek@vitens.nl
License: Apache Licence 2.0
Platform: UNKNOWN
